planekit/Calculator.py
planekit/__init__.py
planekit/command/DoReposition.py
planekit/command/FightMode.py
planekit/command/SetArm.py
planekit/command/TakeOffLandCMD.py
planekit/command/__init__.py
planekit/data/Ahrs.py
planekit/data/Attributes.py
planekit/data/Gps.py
planekit/data/Heartbeat.py
planekit/data/HudMetrics.py
planekit/data/Imu.py
planekit/data/__init__.py
planekit/exception/ConnectionIsNoneError.py
planekit/exception/Error.py
planekit/exception/__init__.py
planekit/mavlink/Connection.py
planekit/mavlink/ReceiveData.py
planekit/mavlink/SendMessage.py
planekit/mavlink/__init__.py
planekit-55.1.907.dist-info/METADATA
planekit-55.1.907.dist-info/WHEEL
planekit-55.1.907.dist-info/top_level.txt
planekit-55.1.907.dist-info/RECORD
